lago/__init__.py
lago/add_ons.py
lago/billable_metrics.py
lago/coupons.py
lago/credit_notes.py
lago/customers.py
lago/events.py
lago/fees.py
lago/invoices.py
lago/organizations.py
lago/plans.py
lago/sdk.py
lago/subscriptions.py
lago/wallets.py
lago/webhooks.py
lago/models/__init__.py
lago/models/operations/__init__.py
lago/models/operations/applyaddon.py
lago/models/operations/applycoupon.py
lago/models/operations/createaddon.py
lago/models/operations/createbatchevents.py
lago/models/operations/createbillablemetric.py
lago/models/operations/createcoupon.py
lago/models/operations/createcreditnote.py
lago/models/operations/createcustomer.py
lago/models/operations/createevent.py
lago/models/operations/createplan.py
lago/models/operations/createsubscription.py
lago/models/operations/createwallet.py
lago/models/operations/createwallettransaction.py
lago/models/operations/deleteappliedcoupon.py
lago/models/operations/deletecustomer.py
lago/models/operations/destroyaddon.py
lago/models/operations/destroybillablemetric.py
lago/models/operations/destroycoupon.py
lago/models/operations/destroyplan.py
lago/models/operations/destroysubscription.py
lago/models/operations/destroywallet.py
lago/models/operations/downloadcreditnote.py
lago/models/operations/downloadinvoice.py
lago/models/operations/eventestimatefees.py
lago/models/operations/fetchpublickey.py
lago/models/operations/finalizeinvoice.py
lago/models/operations/findaddon.py
lago/models/operations/findalladdons.py
lago/models/operations/findallappliedcoupons.py
lago/models/operations/findallbillablemetricgroups.py
lago/models/operations/findallbillablemetrics.py
lago/models/operations/findallcoupons.py
lago/models/operations/findallcreditnotes.py
lago/models/operations/findallcustomers.py
lago/models/operations/findallfees.py
lago/models/operations/findallinvoices.py
lago/models/operations/findallplans.py
lago/models/operations/findallsubscriptions.py
lago/models/operations/findallwallets.py
lago_billing-1.0.1.dist-info/LICENSE.md
lago_billing-1.0.1.dist-info/METADATA
lago_billing-1.0.1.dist-info/WHEEL
lago_billing-1.0.1.dist-info/top_level.txt
lago_billing-1.0.1.dist-info/RECORD
